{"errors":[],"warnings":[],"namedChunkGroups":{"app":{"chunks":[10,0,2],"assets":["webpack-runtime-320660da4cd0aabca7de.js","webpack-runtime-320660da4cd0aabca7de.js.map","commons-62065fb3467a776ac39b.js","commons-62065fb3467a776ac39b.js.map","app-c98f43b00657abe07436.js","app-c98f43b00657abe07436.js.map"],"children":{},"childAssets":{}},"component---src-templates-soap-template-js":{"chunks":[1,0,9],"assets":["styles.df9f6026f39a34dc870c.css","styles-46e0e26cf4fc3c90315b.js","styles-46e0e26cf4fc3c90315b.js.map","commons-62065fb3467a776ac39b.js","commons-62065fb3467a776ac39b.js.map","component---src-templates-soap-template-js-28d79e2efc9ff8d1b004.js","component---src-templates-soap-template-js-28d79e2efc9ff8d1b004.js.map"],"children":{},"childAssets":{}},"component---src-pages-404-js":{"chunks":[1,0,3],"assets":["styles.df9f6026f39a34dc870c.css","styles-46e0e26cf4fc3c90315b.js","styles-46e0e26cf4fc3c90315b.js.map","commons-62065fb3467a776ac39b.js","commons-62065fb3467a776ac39b.js.map","component---src-pages-404-js-baec5af26a872af89854.js","component---src-pages-404-js-baec5af26a872af89854.js.map"],"children":{},"childAssets":{}},"component---src-pages-index-js":{"chunks":[1,0,4],"assets":["styles.df9f6026f39a34dc870c.css","styles-46e0e26cf4fc3c90315b.js","styles-46e0e26cf4fc3c90315b.js.map","commons-62065fb3467a776ac39b.js","commons-62065fb3467a776ac39b.js.map","component---src-pages-index-js-1e2fae24eb3826c82602.js","component---src-pages-index-js-1e2fae24eb3826c82602.js.map"],"children":{},"childAssets":{}},"component---src-pages-products-js":{"chunks":[1,0,5],"assets":["styles.df9f6026f39a34dc870c.css","styles-46e0e26cf4fc3c90315b.js","styles-46e0e26cf4fc3c90315b.js.map","commons-62065fb3467a776ac39b.js","commons-62065fb3467a776ac39b.js.map","component---src-pages-products-js-f003c6bb36b38f48b1dc.js","component---src-pages-products-js-f003c6bb36b38f48b1dc.js.map"],"children":{},"childAssets":{}},"component---src-pages-story-js":{"chunks":[1,0,6],"assets":["styles.df9f6026f39a34dc870c.css","styles-46e0e26cf4fc3c90315b.js","styles-46e0e26cf4fc3c90315b.js.map","commons-62065fb3467a776ac39b.js","commons-62065fb3467a776ac39b.js.map","component---src-pages-story-js-384425ede9e200ded787.js","component---src-pages-story-js-384425ede9e200ded787.js.map"],"children":{},"childAssets":{}},"component---src-pages-team-js":{"chunks":[1,0,7],"assets":["styles.df9f6026f39a34dc870c.css","styles-46e0e26cf4fc3c90315b.js","styles-46e0e26cf4fc3c90315b.js.map","commons-62065fb3467a776ac39b.js","commons-62065fb3467a776ac39b.js.map","component---src-pages-team-js-91dbbb3df4669c7ed005.js","component---src-pages-team-js-91dbbb3df4669c7ed005.js.map"],"children":{},"childAssets":{}},"component---src-pages-test-js":{"chunks":[1,0,8],"assets":["styles.df9f6026f39a34dc870c.css","styles-46e0e26cf4fc3c90315b.js","styles-46e0e26cf4fc3c90315b.js.map","commons-62065fb3467a776ac39b.js","commons-62065fb3467a776ac39b.js.map","component---src-pages-test-js-8c39cf155eb0cc433909.js","component---src-pages-test-js-8c39cf155eb0cc433909.js.map"],"children":{},"childAssets":{}}},"assetsByChunkName":{"app":["webpack-runtime-320660da4cd0aabca7de.js","commons-62065fb3467a776ac39b.js","app-c98f43b00657abe07436.js"],"component---src-templates-soap-template-js":["styles.df9f6026f39a34dc870c.css","styles-46e0e26cf4fc3c90315b.js","commons-62065fb3467a776ac39b.js","component---src-templates-soap-template-js-28d79e2efc9ff8d1b004.js"],"component---src-pages-404-js":["styles.df9f6026f39a34dc870c.css","styles-46e0e26cf4fc3c90315b.js","commons-62065fb3467a776ac39b.js","component---src-pages-404-js-baec5af26a872af89854.js"],"component---src-pages-index-js":["styles.df9f6026f39a34dc870c.css","styles-46e0e26cf4fc3c90315b.js","commons-62065fb3467a776ac39b.js","component---src-pages-index-js-1e2fae24eb3826c82602.js"],"component---src-pages-products-js":["styles.df9f6026f39a34dc870c.css","styles-46e0e26cf4fc3c90315b.js","commons-62065fb3467a776ac39b.js","component---src-pages-products-js-f003c6bb36b38f48b1dc.js"],"component---src-pages-story-js":["styles.df9f6026f39a34dc870c.css","styles-46e0e26cf4fc3c90315b.js","commons-62065fb3467a776ac39b.js","component---src-pages-story-js-384425ede9e200ded787.js"],"component---src-pages-team-js":["styles.df9f6026f39a34dc870c.css","styles-46e0e26cf4fc3c90315b.js","commons-62065fb3467a776ac39b.js","component---src-pages-team-js-91dbbb3df4669c7ed005.js"],"component---src-pages-test-js":["styles.df9f6026f39a34dc870c.css","styles-46e0e26cf4fc3c90315b.js","commons-62065fb3467a776ac39b.js","component---src-pages-test-js-8c39cf155eb0cc433909.js"]}}